{"type":"PR","pr":{"number":89,"head":"83e66e76da466fd076fcecbced6f17563dcf0fe6"},"user":"Willian Justen ","status":"pending_publish","branch":"cms/2018-05-15-meus-20-dias-no-peru","collection":"post","title":"Meus 20 dias no Peru","description":"Um pouco do roteiro que fiz, lugares que me hospedei, trilhas que fiz, meus equipamentos e mais.","objects":{"entry":{"path":"_posts/2018-05-15-meus-20-dias-no-peru.md","sha":"e46e11b299cd76ffb4503cae9c33db8bb3904ca5"},"files":[]},"timeStamp":"2018-11-10T16:39:45.296Z"}